show_dialog/__init__.py
show_dialog/config.py
show_dialog/data_class.py
show_dialog/exit_code.py
show_dialog/inputs.py
show_dialog/main.py
show_dialog/style.py
show_dialog/utils_qt.py
show_dialog/ipc/__init__.py
show_dialog/ipc/client.py
show_dialog/ipc/ipc_params.py
show_dialog/ipc/message.py
show_dialog/ipc/server.py
show_dialog/ui/__init__.py
show_dialog/ui/show_dialog.py
show_dialog/ui/forms/README.md
show_dialog/ui/forms/__init__.py
show_dialog/ui/forms/resources_rc.py
show_dialog/ui/forms/ui_show_dialog.py
qt_show_dialog-0.9.1.dist-info/entry_points.txt
qt_show_dialog-0.9.1.dist-info/licenses/LICENSE.txt
qt_show_dialog-0.9.1.dist-info/WHEEL
qt_show_dialog-0.9.1.dist-info/METADATA
qt_show_dialog-0.9.1.dist-info/RECORD
