Metadata-Version: 2.4
Name: qt-show-dialog
Version: 0.9.1
Summary: Easily show a dialog window for miscellaneous purposes.
Keywords: python,qt,qt6,testing,manual
Author: Joao Coelho
Requires-Python: >=3.10
Classifier: License :: OSI Approved :: MIT License
License-File: LICENSE.txt
Requires-Dist: markdown
Requires-Dist: mashumaro
Requires-Dist: pyside6
Requires-Dist: pyyaml
Requires-Dist: qdarkstyle
Project-URL: Documentation, https://joaonc.github.io/show_dialog
Project-URL: Home, https://github.com/joaonc/show_dialog
